pygreeter/__init__.py
pygreeter/__main__.py
pygreeter/greet/__init__.py
pygreeter/greet/_utils.py
pygreeter-0.1.1.dist-info/METADATA
pygreeter-0.1.1.dist-info/WHEEL
pygreeter-0.1.1.dist-info/licenses/LICENSE
pygreeter-0.1.1.dist-info/RECORD
